jsonype/__init__.py
jsonype/base_types.py
jsonype/basic_from_json_converters.py
jsonype/basic_to_json_converters.py
jsonype/dataclass_converters.py
jsonype/named_tuple_converters.py
jsonype/py.typed
jsonype/simple_str_based_converters.py
jsonype/time_converters.py
jsonype/typed_json.py
jsonype-0.6.1.dist-info/LICENSE
jsonype-0.6.1.dist-info/METADATA
jsonype-0.6.1.dist-info/WHEEL
jsonype-0.6.1.dist-info/RECORD
