Metadata-Version: 2.3
Name: jsonype
Version: 0.6.1
Summary: A package for converting classes with type hints to/from JSON
License: Apache-2.0
Keywords: json
Author: Volker Stampa
Author-email: Volker.Stampa@gmx.net
Maintainer: Volker Stampa
Maintainer-email: Volker.Stampa@gmx.net
Requires-Python: >=3.11,<4.0
Classifier: Development Status :: 4 - Beta
Classifier: Intended Audience :: Developers
Classifier: License :: OSI Approved :: Apache Software License
Classifier: Programming Language :: Python :: 3
Classifier: Programming Language :: Python :: 3.11
Classifier: Programming Language :: Python :: 3.12
Classifier: Programming Language :: Python :: 3.13
Classifier: Programming Language :: Python :: 3 :: Only
Classifier: Topic :: Software Development :: Libraries
Project-URL: Homepage, https://github.com/volkerstampa/jsonype
